mcp_server_gaokao/__init__.py
mcp_server_gaokao/__main__.py
mcp_server_gaokao/data/all_headers.json
mcp_server_gaokao/data/all_major.json
mcp_server_gaokao/server.py
mcp_server_gaokao/tools/__init__.py
mcp_server_gaokao/tools/base.py
mcp_server_gaokao/tools/query_major_info.py
mcp_server_gaokao/utils/__init__.py
mcp_server_gaokao/utils/get_data.py
mcp_server_gaokao/utils/schema.py
mcp_server_gaokao-0.1.7.dist-info/WHEEL
mcp_server_gaokao-0.1.7.dist-info/entry_points.txt
mcp_server_gaokao-0.1.7.dist-info/METADATA
mcp_server_gaokao-0.1.7.dist-info/RECORD
