Metadata-Version: 2.3
Name: mcp-server-gaokao
Version: 0.1.7
Summary: Add your description here
Requires-Dist: mcp>=1.12.3
Requires-Dist: requests>=2.32.4
Requires-Dist: starlette>=0.47.2
Requires-Python: >=3.13
